{"name":"Seleccion de una fecha especifica en un mes diferente al actual","id":"seleccionar-fecha-en-el-campo-de-formulario-de-datepicker;seleccion-de-una-fecha-especifica-en-un-mes-diferente-al-actual","scenarioId":"selecion_fecha:Seleccion de una fecha especifica en un mes diferente al actual","methodName":"Seleccion de una fecha especifica en un mes diferente al actual","testSteps":[{"number":1,"description":"Dado que la usuaria abre la pagina del datepicker","duration":2421,"startTime":"2025-12-15T14:35:18.642236400-05:00[America/Bogota]","screenshots":[{"screenshot":"4e3cdd2931e07498106d16a6cffee723bad30ad2afc952ac8dcf672b456a8103.png","timeStamp":1765827321063,"screenshotName":"4e3cdd2931e07498106d16a6cffee723bad30ad2afc952ac8dcf672b456a8103.png"}],"result":"SUCCESS","precondition":false,"level":0,"children":[{"number":2,"description":"Navegar a la pagina airbnb abrir navegador task","duration":2246,"startTime":"2025-12-15T14:35:18.807079-05:00[America/Bogota]","screenshots":[{"screenshot":"4e3cdd2931e07498106d16a6cffee723bad30ad2afc952ac8dcf672b456a8103.png","timeStamp":1765827321053,"screenshotName":"4e3cdd2931e07498106d16a6cffee723bad30ad2afc952ac8dcf672b456a8103.png"}],"result":"SUCCESS","precondition":false,"level":1,"children":[{"number":3,"description":"Navegar a la pagina airbnb opens the browser at https://jqueryui.com/datepicker/","duration":2216,"startTime":"2025-12-15T14:35:18.823725700-05:00[America/Bogota]","screenshots":[{"screenshot":"4e3cdd2931e07498106d16a6cffee723bad30ad2afc952ac8dcf672b456a8103.png","timeStamp":1765827321039,"screenshotName":"4e3cdd2931e07498106d16a6cffee723bad30ad2afc952ac8dcf672b456a8103.png"}],"result":"SUCCESS","precondition":false,"level":2}]}]}],"userStory":{"id":"selecion_fecha","storyName":"Seleccionar fecha en el campo de formulario de DatePicker","displayName":"Seleccionar fecha en el campo de formulario de DatePicker","path":"selecion_fecha","pathElements":[{"name":"selecion_fecha","description":""}],"narrative":"  Como cristina usuaria de la aplicacion DatePicker\n  Quiero seleccionar una fecha desde el calendario emergente usando datos desde un archivo excel\n  Para evitar errores al ingresar fechas manualmente","type":"feature"},"title":"Seleccion de una fecha especifica en un mes diferente al actual","description":"","tags":[{"name":"FechaMesDiferenteAlActual","type":"tag","displayName":"FechaMesDiferenteAlActual","rawStringFromValueTag":"FechaMesDiferenteAlActual"},{"name":"Chrome","type":"context","displayName":"Chrome"},{"name":"Windows","type":"context","displayName":"Windows"},{"name":"Chrome, Windows","type":"context","displayName":"Chrome, Windows"}],"startTime":"2025-12-15T14:35:18.592834600-05:00[America/Bogota]","endTime":"2025-12-15T14:35:21.064262200-05:00[America/Bogota]","duration":2151,"projectKey":"","sessionId":"443aa2fe02e87c6fdb0796dc7ab5269a","driver":"chrome:navegar a la pagina airbnb","isManualTestingUpToDate":false,"context":"chrome,windows","manual":false,"testSource":"Cucumber","actors":[{"name":"Navegar a la pagina airbnb","can":["browse the web"]}],"order":0,"result":"SUCCESS"}